[{"id":0,"title":"feWorkflow - 使用electron, react, redux, immutable构建桌面App","subtitle":"使用react, redux, immutable框架做ui开发，仍然基于运行gulpfile的方案，这样可以使每个使用自己团队的gulp工作流快速接入和自由调整。","cover":"/img/post///img.aotu.io/FqMe96r-4Spj-juPOP-rH50-oaKX","url":"https://aotu.io/notes/2016/07/05/fe-workflow/","path":"/notes/2016/07/05/fe-workflow/","tags":"React,Electron","categories":"Node.js"},{"id":1,"title":"第二界HiFSD分享会PPT讲义下载分享","subtitle":"HiFSD, 全称Hi Full Stack Developver, 意在定期邀请不同BG、不同团队甚至不同公司的设计或开发团队进行交流，实现知识共享、经验互取等目的，为个人成为全栈工程师而努力。","cover":"/img/post///img.aotu.io/FhrSTu6ppPfs8nqoRU-l9whgbdPB","url":"https://aotu.io/notes/2016/07/03/HIFSD2-Summary/","path":"/notes/2016/07/03/HIFSD2-Summary/","tags":"HiFSD,分享会","categories":"项目总结"},{"id":2,"title":"神奇的Shadow DOM","subtitle":"Shadow DOM可以做什么，好奇就看过来！","cover":"http://7xt3gj.com1.z0.glb.clouddn.com/FgHV3-D9eRTz1L6CNQht0jo6a4lt","url":"https://aotu.io/notes/2016/06/24/Shadow-DOM/","path":"/notes/2016/06/24/Shadow-DOM/","tags":"Git,Fork","categories":""},{"id":3,"title":"探究WebP一些事儿","subtitle":"WebP图片格式是提升用户体验的一大利器，本文通过探究WebP的一些细节来说明WebP能够给我们带来的提升。","cover":"/img/post///img.aotu.io/FufVMQ_IV5Z_fGJa12AHNgs63sR2","url":"https://aotu.io/notes/2016/06/23/explore-something-of-webp/","path":"/notes/2016/06/23/explore-something-of-webp/","tags":"WebP,图片","categories":"性能优化"},{"id":4,"title":"让console充满情怀","subtitle":"打开console控制台,你有一份前端情怀在这里~~","cover":"/img/post///img.aotu.io/FiLwh8e3l--mGdsJNw3Bm-Z8o_JF","url":"https://aotu.io/notes/2016/06/22/An-interesting-experience-on-console/","path":"/notes/2016/06/22/An-interesting-experience-on-console/","tags":"console,占位符,字符画","categories":""},{"id":5,"title":"假如HTTP/2已经普及","subtitle":"HTTP/2 时代已经来临，对于我们前端它具体会带来什么改变呢？原本的性能优化还能用么？代码上有什么差异呢？","cover":"/img/post///img.aotu.io/FrKbasT5AE4Hf5S3MEAIVmFosQiB","url":"https://aotu.io/notes/2016/06/14/http2/","path":"/notes/2016/06/14/http2/","tags":"HTTP/2,前端技术","categories":"Web开发"},{"id":6,"title":"Adobe Spark试用手记","subtitle":"5月，夏，初夏。一个不起眼的日子，起眼的是一家公司，一款产品，它叫Adobe，它叫Spark。没有人知道Adobe究竟有没有发布过多终端产品，真正意义的多终端产品，它俨然动手了，就在一周之前，干脆利落，不带一丝迟疑。","cover":"/img/post///img.aotu.io/FmSA1_Z0xxMrGrTJ0p8VVignufIZ","url":"https://aotu.io/notes/2016/05/27/adobe-spark/","path":"/notes/2016/05/27/adobe-spark/","tags":"Spark,新品试用","categories":"其他"},{"id":7,"title":"CSS3动画之逐帧动画","subtitle":"CSS3动画开发指南第二弹","cover":"/img/post///img.aotu.io/Yettyzyt/css3-animation-frame/840.png","url":"https://aotu.io/notes/2016/05/17/css3-animation-frame/","path":"/notes/2016/05/17/css3-animation-frame/","tags":"动画","categories":"Web开发"},{"id":8,"title":"CSS3动画之补间动画","subtitle":"CSS3动画开发指南第一弹","cover":"/img/post///img.aotu.io/Tingglelaoo/20160506/TweenAnimation_cover.png","url":"https://aotu.io/notes/2016/05/06/Guide-To-Tween-Animation/","path":"/notes/2016/05/06/Guide-To-Tween-Animation/","tags":"CSS3,动画,Aniamtion","categories":"Web开发"},{"id":9,"title":"CSS3动画之3D动画","subtitle":"CSS3动画开发指南第三弹","cover":"/img/post///img.aotu.io/FrYNVc2GU23S0lHWu4xwzQtd7PR5","url":"https://aotu.io/notes/2016/05/06/CSS3-3D-Animation/","path":"/notes/2016/05/06/CSS3-3D-Animation/","tags":"CSS3,动画,H5,触屏页,3D","categories":"Web开发"},{"id":10,"title":"Swift Package Manager 快速入门指引","subtitle":"带你快速上手 Swift Package Manager","cover":"/img/post///img.aotu.io/MarkLin/SPM/SPM_cover.png","url":"https://aotu.io/notes/2016/04/28/SPM/","path":"/notes/2016/04/28/SPM/","tags":"iOS,Swift","categories":"移动开发"},{"id":11,"title":"如何用ArrayBuffer构造一个form请求","subtitle":"form表单数据编码类型为multi/formdata的分析","cover":"http://storage.jd.com/o2team/home/formrequest_cover1461222741603.png","url":"https://aotu.io/notes/2016/04/21/form-request/","path":"/notes/2016/04/21/form-request/","tags":"form,xhr2,ArrayBuffer,构造form数据","categories":"Web开发"},{"id":12,"title":"JavaScript中reduce()方法不完全指南","subtitle":"实例讲解了ES5中reduce方法的用法","cover":"http://7xt3gj.com1.z0.glb.clouddn.com/panxinwu/reduce_cover.png","url":"https://aotu.io/notes/2016/04/15/2016-04-14-js-reduce/","path":"/notes/2016/04/15/2016-04-14-js-reduce/","tags":"JavaScript,reduce","categories":"Web开发"},{"id":13,"title":"JavaScript中Math.random的种子设定方法","subtitle":"曾为JS中无法设定种子随机数而苦恼吧？实例讲解了JS中种子随机数的设定方法","cover":"http://7xt3gj.com1.z0.glb.clouddn.com/panxinwu/mathrandom_cover.png","url":"https://aotu.io/notes/2016/04/15/2016-04-14-math-random/","path":"/notes/2016/04/15/2016-04-14-math-random/","tags":"JavaScript,Random","categories":"Web开发"},{"id":14,"title":"Canvas虹膜消除转场","subtitle":"一条基于童年动画记忆的考据之路","cover":"http://7xt3gj.com1.z0.glb.clouddn.com/lyxuncle/iriswipe/iriswipe_cover.png","url":"https://aotu.io/notes/2016/04/13/Iris-Wipe/","path":"/notes/2016/04/13/Iris-Wipe/","tags":"Canvas,转场,触屏页转场,消除转场,虹膜","categories":"Web开发"},{"id":15,"title":"前端优化实践总结","subtitle":"结合项目总结优化过程中如何寻找优化点以及收益比较大的常见方法，希望可以对遇到相似问题的同学有帮助，前端大神可轻轻淡笑而过。","cover":"http://7xt3gj.com1.z0.glb.clouddn.com/mihanX/jcloud-opt/banner3.png","url":"https://aotu.io/notes/2016/04/12/jcloud-opt/","path":"/notes/2016/04/12/jcloud-opt/","tags":"项目总结,页面优化","categories":"项目总结"},{"id":16,"title":"Node读写Excel文件探究实践","subtitle":"本文介绍用 Node.js 中的依赖库来处理 Excel 文件，主要阐述用js-xlsx、excel-export 库来处理 Excel 文件。","cover":"http://7xt3gj.com1.z0.glb.clouddn.com/pfan/excel/n_excel.png","url":"https://aotu.io/notes/2016/04/07/node-excel/","path":"/notes/2016/04/07/node-excel/","tags":"node,excel,JS-XLSX,Node-Excel-Export","categories":"Node.js"},{"id":17,"title":"提升代码的可读性系列(一)--基础篇","subtitle":"一切不以可读性为前提的写代码，都是耍流氓","cover":"/img/post///img.aotu.io/yangzicheng/2016-03-31-readable/readable_cover.png","url":"https://aotu.io/notes/2016/03/31/readable/","path":"/notes/2016/03/31/readable/","tags":"编码风格,变量,UI松耦合,错误处理,创建对象,可读性,可维护性","categories":"Web开发"},{"id":18,"title":"如何优雅地在Storyboard中设置圆角","subtitle":"在Storyboard中设置圆角的正确打开方式~","cover":"/img/post///img.aotu.io/MarkLin/cornerRadius/CornerRadius.png","url":"https://aotu.io/notes/2016/03/30/cornerRadius-in-Storyboard/","path":"/notes/2016/03/30/cornerRadius-in-Storyboard/","tags":"iOS,Swift","categories":"iOS"},{"id":19,"title":"前端开发与 HTTP/2 的羁绊——安利篇","subtitle":"《前端开发与 HTTP/2 的羁绊》系列文章，本文侧重介绍 HTTP/2 在 HTTP/1.x 现有的问题上进行改进，从而产生的新特性，并为读者详细讲解每个特性的特点及其实现。","cover":"/img/post///img.aotu.io/Yettyzyt/http2-1/840.png","url":"https://aotu.io/notes/2016/03/17/http2-char/","path":"/notes/2016/03/17/http2-char/","tags":"HTTP/2","categories":"Web开发"},{"id":20,"title":"前端优化不完全指南","subtitle":"暖妹子の前端优化不完全指南来袭,救赎众生啦～～快来瞧瞧～","cover":"/img/post///img.aotu.io/wangcainuan/2016-03-16-optimization/optimization_cover.png","url":"https://aotu.io/notes/2016/03/16/optimization/","path":"/notes/2016/03/16/optimization/","tags":"工作效率,速度性能,安全性,响应式,兼容性,搜索SEO,信息无障碍,前端优化","categories":"性能优化"},{"id":21,"title":"某超长文档的探索之路","subtitle":"加量不加价~ 比字数谁都赢不了我!","cover":"/img/post///img.aotu.io/Littly/2016-03-15/title.png","url":"https://aotu.io/notes/2016/03/16/jcloud-sum/","path":"/notes/2016/03/16/jcloud-sum/","tags":"jcloud,sum","categories":"项目总结"},{"id":22,"title":"让图片加载这件事儿变得更美好","subtitle":"图片是触屏页面让人赏心悦目的重要元素之一。而对图片资源的加载渲染将影响页面呈现，处理好图片加载才能给用户更好的体验。","cover":"/img/post///img.aotu.io/Tingglelaoo/20160302/load_cover_840x340.png","url":"https://aotu.io/notes/2016/03/09/img-loading-optimization-in-mobile/","path":"/notes/2016/03/09/img-loading-optimization-in-mobile/","tags":"Images,Load,optimize,Mobile","categories":"性能优化"},{"id":23,"title":"图片资源Base64化在H5页面里有用武之地吗？","subtitle":"本文使用performance接口和Timeline工具，测试和分析了不同场景下引用base64化的图片资源对渲染性能的影响，旨在抛砖引玉，找出图片资源的base64化在H5应用中使用的可行性。","cover":"/img/post///img.aotu.io/Simbachen/base64/cover.jpg","url":"https://aotu.io/notes/2016/03/04/can-we-use-base64-in-h5-webapps/","path":"/notes/2016/03/04/can-we-use-base64-in-h5-webapps/","tags":"base64,h5","categories":"性能优化"},{"id":24,"title":"createjs开发入门","subtitle":"通过实例浅析createjs","cover":"/img/post///img.aotu.io/youing/20160229/createjs-get-started-cover.jpg","url":"https://aotu.io/notes/2016/03/01/createjs-get-started/","path":"/notes/2016/03/01/createjs-get-started/","tags":"createjs,tweenjs,zoe,preloadjs,soundjs,easeljs","categories":"Web开发"},{"id":25,"title":"初探Docker","subtitle":"docker：一个开源的引擎，可以轻松的为任何应用创建一个轻量级的、可移植的、自给自足的容器，能够快速部署你的应用","cover":"/img/post///img.aotu.io/lizhi/docker/banner.png","url":"https://aotu.io/notes/2016/02/27/docker/","path":"/notes/2016/02/27/docker/","tags":"docker,环境,部署,docker hub","categories":"Web开发"},{"id":26,"title":"使用npm scripts替代gulp","subtitle":"利用npm run高效地实现前端自动化任务","cover":"/img/post///img.aotu.io/cnt1992/npm-instead-of-gulp-cover.png","url":"https://aotu.io/notes/2016/02/26/use-npm-script-instead-of-gulp/","path":"/notes/2016/02/26/use-npm-script-instead-of-gulp/","tags":"Git,Fork","categories":"Node.js"},{"id":27,"title":"Node 生产环境调试","subtitle":"本文以问答的形式，介绍生产环境中该如何去调试 Node 应用。","cover":"/img/post///img.aotu.io/chuyik/node_debug_in_production_cover.png","url":"https://aotu.io/notes/2016/02/24/node-debug-in-production/","path":"/notes/2016/02/24/node-debug-in-production/","tags":"调试,node","categories":"Node.js"},{"id":28,"title":"手把手教你搭建ngrok服务－轻松外网调试本机站点","subtitle":"ngrok的核心功能：能够将你本机的HTTP服务（站点）或TCP服务，通过部署有ngrok服务的外网伺服器暴露给外网访问！","cover":"/img/post///img.aotu.io/mamboer/ngrok.jpg","url":"https://aotu.io/notes/2016/02/19/ngrok/","path":"/notes/2016/02/19/ngrok/","tags":"ngrok,反向代理,调试","categories":"Web开发"},{"id":29,"title":"你所知道的3xx状态码","subtitle":"介绍了3xx系列状态码，以及缓存、网页劫持一些列相关的知识。","cover":"/img/post///img.aotu.io/wengeek/3xx_cover.png","url":"https://aotu.io/notes/2016/01/28/3xx-of-http-status/","path":"/notes/2016/01/28/3xx-of-http-status/","tags":"http,重定向,缓存","categories":"Web开发"},{"id":30,"title":"如何制作cocoaPods依赖库","subtitle":"本文介绍如何制作cocoaPods依赖库","cover":"/img/post///img.aotu.io/MarkLin/cocoaPods/CocoaPods.png","url":"https://aotu.io/notes/2016/01/27/how-to-make-cocoapods/","path":"/notes/2016/01/27/how-to-make-cocoapods/","tags":"iOS,CocoaPods","categories":"移动开发"},{"id":31,"title":"如何创建私有 CocoaPods 仓库","subtitle":"本文介绍如何创建私有的 CocoaPods 仓库","cover":"/img/post///img.aotu.io/MarkLin/privateCocoaPods/PrivateCocoaPods.png","url":"https://aotu.io/notes/2016/01/26/Private-CocoaPods-Specs-Repo/","path":"/notes/2016/01/26/Private-CocoaPods-Specs-Repo/","tags":"iOS,CocoaPods,Swift","categories":"移动开发"},{"id":32,"title":"UFT 需求提报平台回顾","subtitle":"展现需求提交平台从无到有的过程，及分享实践中的经验。","cover":"/img/post///img.aotu.io/Manjiz/2016/uft/uft_cover.png","url":"https://aotu.io/notes/2016/01/16/UFT/","path":"/notes/2016/01/16/UFT/","tags":"uft,angular,kendo,node-mysql,express","categories":"项目总结"},{"id":33,"title":"js游戏开发初级入门","subtitle":"凹凸实验室水灵通透软妹子－暖暖，手把手教你用js开发五子棋游戏！","cover":"/img/post///img.aotu.io/wangcainuan/2016-01-14-introduction-to-JS-game-development/gobang_cover.jpg","url":"https://aotu.io/notes/2016/01/14/introduction-to-JS-game-development/","path":"/notes/2016/01/14/introduction-to-JS-game-development/","tags":"js,游戏,五子棋","categories":"Web开发"},{"id":34,"title":"Promise 实战","subtitle":"本文适合对Promise已有一定了解的同学，如果你还不知道Promise是什么，可以移步这里<a target=\"blank\" href=\"https://developer.mozilla.org/zh-CN/docs/Web/JavaScript/Reference/Global_Objects/Promise\">Promise API的使用方法</a>，掌握基础的Promise使用方法后，再阅读本文。","cover":"/img/post///img.aotu.io/adamchuan/promise-cover.jpg","url":"https://aotu.io/notes/2016/01/08/promise/","path":"/notes/2016/01/08/promise/","tags":"ES6,Promise","categories":"Web开发"},{"id":35,"title":"使用Chrome开发工具优化Web应用","subtitle":"本文主要介绍如何使用Chrome开发工具的Timeline功能来监控Web应用的性能，找出问题，并由此延伸出一些优化Web应用性能的思路。","cover":"/img/post///img.aotu.io/Simbachen/cover.jpg","url":"https://aotu.io/notes/2016/01/07/debug-webapp-with-chrome-devtools/","path":"/notes/2016/01/07/debug-webapp-with-chrome-devtools/","tags":"chrome,DevTool","categories":"性能优化"},{"id":36,"title":"使用Github的webhooks进行网站自动化部署","subtitle":"本文介绍Github的高级功能webhooks，并通过实例帮助我们如何使用它进行网站的自动化部署","cover":"/img/post///img.aotu.io/cnt1992/webhooks-cover.jpg","url":"https://aotu.io/notes/2016/01/07/auto-deploy-website-by-webhooks-of-github/","path":"/notes/2016/01/07/auto-deploy-website-by-webhooks-of-github/","tags":"Github,webhooks","categories":"Web开发"},{"id":37,"title":"CSS3动画实践","subtitle":"总结CSS3动画实现的方法，并进一步提出润色与优化的方案。","cover":"/img/post///img.aotu.io/Yettyzyt/css3-animation/840.png","url":"https://aotu.io/notes/2016/01/04/css3-animation/","path":"/notes/2016/01/04/css3-animation/","tags":"CSS3,animation","categories":"Web开发"},{"id":38,"title":"使用ThreeJS在浏览器中展示全景图","subtitle":null,"cover":"/img/post///img.aotu.io/Littly/2016-01-01/title.png","url":"https://aotu.io/notes/2016/01/02/3D-panorama/","path":"/notes/2016/01/02/3D-panorama/","tags":"three.js,panorama","categories":"Web开发"},{"id":39,"title":"初识Adobe After Effects效果制作","subtitle":"Adobe After Effects简称“AE”是Adobe公司推出的一款图形视频处理软件，用于高端视频特效系统的专业特效合成。","cover":"/img/post///img.aotu.io/pfan/ae/ae.png","url":"https://aotu.io/notes/2015/12/29/ae/","path":"/notes/2015/12/29/ae/","tags":"Adobe After Effects,AE,AE movie","categories":"Web开发"},{"id":40,"title":"【译】使用Node.js创建命令行脚本工具","subtitle":"通过本文将一步步带领你利用Node.js来创建命令行脚本工具","cover":"/img/post///img.aotu.io/cnt1992/command-line-tools.jpg","url":"https://aotu.io/notes/2015/12/23/building-command-line-tools-with-node-js/","path":"/notes/2015/12/23/building-command-line-tools-with-node-js/","tags":"Node.js,command line tools","categories":"Node.js"},{"id":41,"title":"Safari 9.0的新特性","subtitle":"苹果的 OS 在不断发展，Safari 亦越变强大性感，在最新的 9.0 版本当中，Safari 增加了不少新的特性，这里主要介绍一下和 Web 前端密切相关的。","cover":"/img/post///img.aotu.io/mihanX/safari-9/banner.png","url":"https://aotu.io/notes/2015/12/23/new-safari-9/","path":"/notes/2015/12/23/new-safari-9/","tags":"Safari 9.0,iOS,OS X","categories":"其它"},{"id":42,"title":"What Does the Foo Mean","subtitle":"以前在不少编程书里经常看到 “foo”、“bar” 这对 couple，一直不知道他们的具体含义，于是默默去 google 搜了一下，发现结果还挺有意思","cover":"/img/post///img.aotu.io/mihanX/foo-banner.png","url":"https://aotu.io/notes/2015/12/18/etymology-of-foobar/","path":"/notes/2015/12/18/etymology-of-foobar/","tags":"Foo","categories":"其它"},{"id":43,"title":"【译】介绍Sass Maps：用法跟例子","subtitle":"本文介绍如何利用Sass Maps简化我们的代码，翻译水平有限，敬请指正。","cover":"/img/post///img.aotu.io/cnt1992/sass-maps-cover.jpg","url":"https://aotu.io/notes/2015/12/09/an-introduction-to-sass-maps/","path":"/notes/2015/12/09/an-introduction-to-sass-maps/","tags":"sass,sass maps","categories":"Web开发"},{"id":44,"title":"Adobe edge animate制作HTML5动画","subtitle":"Edge Animate是Adobe出品的制作HTML5动画的可视化工具，简单的可以理解为HTML5版本的Flash Pro。","cover":"/img/post///img.aotu.io/pfan/edge/edgeanimate.jpg","url":"https://aotu.io/notes/2015/12/04/edgeAnimate/","path":"/notes/2015/12/04/edgeAnimate/","tags":"edge animate,html5,animate","categories":"Web开发"},{"id":45,"title":"使用ThreeJS在浏览器中展示3D物件","subtitle":"看官别走啊，这真不是软文。","cover":"/img/post///img.aotu.io/Littly/title.png","url":"https://aotu.io/notes/2015/11/24/3D-CleaningCream/","path":"/notes/2015/11/24/3D-CleaningCream/","tags":"three.js","categories":"Web开发"},{"id":46,"title":"精致化页面重构","subtitle":"刚完成了一个项目的开发，本文将分享给大家一些项目中的一些经验与小技巧。","cover":"/img/post///img.aotu.io/liqinuo/cover.png","url":"https://aotu.io/notes/2015/11/24/project-summary/","path":"/notes/2015/11/24/project-summary/","tags":"summary","categories":"项目总结"},{"id":47,"title":"以电影之眼看CSS3动画（二）","subtitle":"CSS3动画和电影到底有啥关系？讲了一篇都没讲到，不会是在骗我吧？你这个骗子。","cover":"/img/post///img.aotu.io/lyxuncle/cover.png","url":"https://aotu.io/notes/2015/11/23/css3-animation-to-movie-part_2/","path":"/notes/2015/11/23/css3-animation-to-movie-part_2/","tags":"CSS3,Animation","categories":"Web开发"},{"id":48,"title":"以电影之眼看CSS3动画（一）","subtitle":"要写CSS3动画，必先学技术。要写好CSS3动画，还是得深入探索传统动画的精华。","cover":"/img/post///img.aotu.io/lyxuncle/cover.png","url":"https://aotu.io/notes/2015/11/23/css3-animation-to-movie-part_1/","path":"/notes/2015/11/23/css3-animation-to-movie-part_1/","tags":"CSS3,Animation","categories":"Web开发"},{"id":49,"title":"SVG I Know","subtitle":"SVG即Scalable Vector Graphics可缩放矢量图形，使用XML格式定义图形。","cover":"/img/post///img.aotu.io/Newcandy/svgCover.png","url":"https://aotu.io/notes/2015/11/20/svg-I-know/","path":"/notes/2015/11/20/svg-I-know/","tags":"svg","categories":"Web开发"},{"id":50,"title":"Git常用操作总结","subtitle":"理解Git的内部原理，分清楚工作区、暂存区、版本库，还有就是理解Git跟踪并管理的是修改，而非文件。","cover":"/img/post///img.aotu.io/mamboer/git-flow.jpg","url":"https://aotu.io/notes/2015/11/17/Git-Commands/","path":"/notes/2015/11/17/Git-Commands/","tags":"Git,Fork","categories":"Web开发"},{"id":51,"title":"101%还原","subtitle":"重构工程师不应该满足100%还原设计稿，更应该去追求101%还原度","cover":"/img/post///img.aotu.io/mihanX/mihan-101-percent.png","url":"https://aotu.io/notes/2015/11/16/101-percent/","path":"/notes/2015/11/16/101-percent/","tags":"设计理念还原","categories":"Web开发"},{"id":52,"title":"基于phantomJs的网络爬虫","subtitle":"phantomJs是一个基于WebKit的服务器端JavaScript API。可以用于页面自动化，网络监测，网页截屏，以及无界面测试等。","cover":"/img/post///img.aotu.io/panxinwu/phantomjs.png","url":"https://aotu.io/notes/2015/11/11/phantomJs-crawler/","path":"/notes/2015/11/11/phantomJs-crawler/","tags":"PhantomJS,Crawler","categories":"Web开发"},{"id":53,"title":"css层叠顺序探究","subtitle":"A stacking context is formed, anywhere in the document, by any element which is either","cover":"/img/post///img.aotu.io/Yettyzyt/cover.png","url":"https://aotu.io/notes/2015/11/08/css-stack-order/","path":"/notes/2015/11/08/css-stack-order/","tags":"CSS","categories":"Web开发"},{"id":54,"title":"Service Workers：采用WebP动态响应图片","subtitle":"你可能听过**WebP**图片格式。相比于PNG图片，其文件大小能够节省26％；相比于JPEG图片，能够节省大约25％。","cover":"/img/post///img.aotu.io/wengeek/responsive-image.png","url":"https://aotu.io/notes/2015/11/06/webp-responsive-image/","path":"/notes/2015/11/06/webp-responsive-image/","tags":"WebP","categories":"性能优化"},{"id":55,"title":"使用Adobe FLASH CC制作Canvas动画","subtitle":"flash可以导出canvas动画，大大缩短制作动画所需要的时间。它是可视化IDE，可以让我们写少很多代码。做出来的动画，可以更加精确。","cover":"/img/post///img.aotu.io/youing/flash-canvas.png","url":"https://aotu.io/notes/2015/11/02/flash-canvas/","path":"/notes/2015/11/02/flash-canvas/","tags":"Flash,Canvas","categories":"Web开发"},{"id":56,"title":"前方有坑，请绕道——Zepto 中使用 CORS","subtitle":"一直以来，我们在移动端上面使用 zepto 并没有出现太大的问题。直至我们将 Ajax 跨域请求从 iframe 的方式切换成 CORS 之后。","cover":"/img/post///img.aotu.io/Koppthe/cors-zepto.jpg","url":"https://aotu.io/notes/2015/10/26/zepto-cors/","path":"/notes/2015/10/26/zepto-cors/","tags":"Zepto,CORS","categories":"Web开发"},{"id":57,"title":"探究transform动画元素的z-index","subtitle":"transform 变换的时候会让 z-index “临时失效”，其实并非 z-index 失效了，只是 z-index 被用在不同的 `stacking context` 上。","cover":"/img/post///img.aotu.io/Manjiz/2015/manjiz-151116-cover.png","url":"https://aotu.io/notes/2015/10/21/z-index-and-translate3d/","path":"/notes/2015/10/21/z-index-and-translate3d/","tags":"translate3d,zindex","categories":"Web开发"},{"id":58,"title":"我的vim二三事","subtitle":"用了几年Vim，我发现我越来越喜欢它了，和好多人一样喜欢它，也许喜欢的理由各不相同，但大抵有如下几个。","cover":"/img/post///img.aotu.io/huangliyn/vim-list.jpg","url":"https://aotu.io/notes/2015/10/16/vim-list/","path":"/notes/2015/10/16/vim-list/","tags":"Web开发","categories":""},{"id":59,"title":"PostCSS快速入门使用","subtitle":"PostCSS 是一套利用JS插件实现的用来改变CSS的工具.这些插件能够支持变量和混合语法，转换未来CSS语法，内联图片，还有更多","cover":"/img/post///img.aotu.io/cnt1992/postcss.jpg","url":"https://aotu.io/notes/2015/10/13/start-postcss/","path":"/notes/2015/10/13/start-postcss/","tags":"Web开发","categories":""},{"id":60,"title":"凹凸实验室博客V1.0.0发布","subtitle":"凹凸实验室博客是一个托管于Github的静态博客，基于HEXO搭建，主题的定做参考自future-imperfect的扁平简约，暂且命名为`o2`。","cover":"/img/post///img.aotu.io/mamboer/post-aotu.jpg","url":"https://aotu.io/notes/2015/10/08/aotu-blog-v1/","path":"/notes/2015/10/08/aotu-blog-v1/","tags":"Hexo,项目总结","categories":"项目总结"}]